promptlibrary/__init__.py
promptlibrary-0.0.1.dist-info/METADATA
promptlibrary-0.0.1.dist-info/WHEEL
promptlibrary-0.0.1.dist-info/licenses/LICENSE
promptlibrary-0.0.1.dist-info/RECORD
